removebgplus/__init__.py
removebgplus/removebg.py
removebgplus-0.1.2.dist-info/METADATA
removebgplus-0.1.2.dist-info/WHEEL
removebgplus-0.1.2.dist-info/top_level.txt
removebgplus-0.1.2.dist-info/RECORD
