Metadata-Version: 2.4
Name: RemoveBgPlus
Version: 0.1.2
Summary: Python wrapper for the remove.bg API
License: MIT
Requires-Python: >=3.7
Requires-Dist: requests
Requires-Dist: filetype
